[
  {
    "id": "order-1775189473690",
    "drug": "lisinopril",
    "pharmacy": "CVS Pharmacy",
    "amount": 10,
    "status": "confirmed",
    "timestamp": "2026-04-03T04:11:13.690Z",
    "network": "stellar:testnet",
    "protocol": "MPP Charge"
  },
  {
    "id": "order-1775194929490",
    "drug": "lisinopril",
    "pharmacy": "Costco Pharmacy",
    "amount": 3.5,
    "status": "confirmed",
    "timestamp": "2026-04-03T05:42:09.490Z",
    "network": "stellar:testnet",
    "protocol": "MPP Charge"
  },
  {
    "id": "order-1775194935166",
    "drug": "metformin",
    "pharmacy": "Walmart Pharmacy",
    "amount": 4,
    "status": "confirmed",
    "timestamp": "2026-04-03T05:42:15.166Z",
    "network": "stellar:testnet",
    "protocol": "MPP Charge"
  }
]